ag2_ext_yepcode/__init__.py
ag2_ext_yepcode/_yepcode_executor.py
ag2_ext_yepcode/py.typed
ag2_ext_yepcode-0.1.0.dist-info/LICENSE
ag2_ext_yepcode-0.1.0.dist-info/METADATA
ag2_ext_yepcode-0.1.0.dist-info/WHEEL
ag2_ext_yepcode-0.1.0.dist-info/RECORD
