Metadata-Version: 2.3
Name: ag2-ext-yepcode
Version: 0.1.0
Summary: An AG2 (formerly Autogen) extension that allows code execution using YepCode's secure serverless runtime
License: See LICENSE file
Keywords: ag2,autogen,autogen-ext,yepcode,code-execution,serverless
Author: YepCode Developers
Author-email: developers@yepcode.io
Requires-Python: >=3.12,<3.13
Classifier: License :: Other/Proprietary License
Classifier: Programming Language :: Python :: 3
Classifier: Programming Language :: Python :: 3.12
Provides-Extra: examples
Requires-Dist: ag2 (>=0.9.5,<0.10.0) ; extra == "examples"
Requires-Dist: python-dotenv (>=1.0.0,<2.0.0)
Requires-Dist: yepcode-run (>=1.4.0,<2.0.0)
Project-URL: Homepage, https://yepcode.io/
